url2pg/__init__.py
url2pg/__main__.py
url2pg-0.1.0.dist-info/METADATA
url2pg-0.1.0.dist-info/WHEEL
url2pg-0.1.0.dist-info/entry_points.txt
url2pg-0.1.0.dist-info/top_level.txt
url2pg-0.1.0.dist-info/RECORD
