Metadata-Version: 2.4
Name: url2pg
Version: 0.1.0
Summary: This repository ingests data from a CSV/Parquet url into a Postgres table overwriting the previous table if it exists.
Author-email: Cesar Cardoso <hello@cesarcardoso.cc>
License-Expression: MIT
Requires-Python: >=3.10
Requires-Dist: pandas>=2.3.3
Requires-Dist: psycopg2-binary>=2.9.11
Requires-Dist: pyarrow>=22.0.0
Requires-Dist: sqlalchemy>=2.0.45
